pyrhubarb_mcp/__init__.py
pyrhubarb_mcp/cli.py
pyrhubarb_mcp/server.py
pyrhubarb_mcp-0.1.3.dist-info/METADATA
pyrhubarb_mcp-0.1.3.dist-info/WHEEL
pyrhubarb_mcp-0.1.3.dist-info/entry_points.txt
pyrhubarb_mcp-0.1.3.dist-info/RECORD
