Metadata-Version: 2.4
Name: pyrhubarb-mcp
Version: 0.1.3
Summary: MCP server for Rhubarb document and video understanding capabilities
License: Apache 2.0
Author: Rhubarb Developers
Author-email: rhubarb-developers@amazon.com
Requires-Python: >=3.11
Classifier: License :: OSI Approved :: Apache Software License
Classifier: License :: Other/Proprietary License
Classifier: Operating System :: OS Independent
Classifier: Programming Language :: Python :: 3
Classifier: Programming Language :: Python :: 3.11
Classifier: Programming Language :: Python :: 3.12
Classifier: Programming Language :: Python :: 3.13
Classifier: Programming Language :: Python :: 3.14
Requires-Dist: boto3 (>=1.35.20,<2.0.0)
Requires-Dist: botocore (>=1.35.20,<2.0.0)
Requires-Dist: fastmcp (>=0.3.0,<0.4.0)
Requires-Dist: openpyxl (>=2.0.0,<3.0.0)
Requires-Dist: pyrhubarb (>=0.0.7,<0.0.8)
Project-URL: Documentation, https://awslabs.github.io/rhubarb/
Project-URL: Homepage, https://github.com/awslabs/rhubarb
Project-URL: Issues, https://github.com/awslabs/rhubarb/issues
Project-URL: Repository, https://github.com/awslabs/rhubarb
